arguments_parser/__init__.py
arguments_parser-0.0.1.dist-info/METADATA
arguments_parser-0.0.1.dist-info/WHEEL
arguments_parser-0.0.1.dist-info/top_level.txt
arguments_parser-0.0.1.dist-info/RECORD
