Metadata-Version: 2.1
Name: arguments_parser
Version: 0.0.1
Summary: A library to parse command line arguments
Author-email: Danny Vaca <danny270793@gmail.com>
License: The MIT License (MIT)
Project-URL: Homepage, https://github.com/danny270793/arguments_parser
Project-URL: Issues, https://github.com/danny270793/arguments_parser/issues
Keywords: cmd
Classifier: Programming Language :: Python :: 3
Classifier: License :: OSI Approved :: MIT License
Classifier: Operating System :: OS Independent
Requires-Python: >=3.8
